rail/estimation/algos/cc_yaw.py
rail/pipelines/estimation/.gitignore
rail/pipelines/estimation/build_pipeline.py
rail/pipelines/estimation/plot_output.py
rail/pipelines/estimation/run_pipeline.sh
rail/pipelines/estimation/yaw_pipeline.yml
rail/pipelines/estimation/yaw_pipeline_config.yml
rail/yaw_rail/__init__.py
rail/yaw_rail/_version.py
rail/yaw_rail/cache.py
rail/yaw_rail/handles.py
rail/yaw_rail/stage_config.py
rail/yaw_rail/utils.py
pz_rail_yaw-1.1.1.dist-info/LICENSE
pz_rail_yaw-1.1.1.dist-info/METADATA
pz_rail_yaw-1.1.1.dist-info/WHEEL
pz_rail_yaw-1.1.1.dist-info/top_level.txt
pz_rail_yaw-1.1.1.dist-info/RECORD
