Metadata-Version: 2.2
Name: pz-rail-yaw
Version: 1.1.1
Summary: Wrapper around the yet_another_wizz clustering redshift code for RAIL
Author-email: "LSST Dark Energy Science Collaboration (DESC)" <lsst-desc-rail-admin@slac.stanford.edu>
License: MIT License
Project-URL: Repository, https://github.com/LSSTDESC/rail_yaw.git
Classifier: Development Status :: 4 - Beta
Classifier: License :: OSI Approved :: MIT License
Classifier: Intended Audience :: Developers
Classifier: Intended Audience :: Science/Research
Classifier: Operating System :: OS Independent
Classifier: Programming Language :: Python
Requires-Python: >=3.10
License-File: LICENSE
Requires-Dist: numpy
Requires-Dist: h5py
Requires-Dist: pandas
Requires-Dist: pz-rail-base>=1.0.3
Requires-Dist: yet_another_wizz>=3.1.0
Provides-Extra: dev
Requires-Dist: pytest; extra == "dev"
Requires-Dist: pytest-cov; extra == "dev"
Requires-Dist: pytest-skip-slow; extra == "dev"
Requires-Dist: pre-commit; extra == "dev"
Requires-Dist: pylint; extra == "dev"
Requires-Dist: black; extra == "dev"
Requires-Dist: nbconvert; extra == "dev"
